README.rst
setup.cfg
setup.py
src/markdown_to_devto/__init__.py
src/markdown_to_devto/cli.py
src/markdown_to_devto/http_client.py
src/markdown_to_devto.egg-info/PKG-INFO
src/markdown_to_devto.egg-info/SOURCES.txt
src/markdown_to_devto.egg-info/dependency_links.txt
src/markdown_to_devto.egg-info/entry_points.txt
src/markdown_to_devto.egg-info/not-zip-safe
src/markdown_to_devto.egg-info/requires.txt
src/markdown_to_devto.egg-info/top_level.txt
src/markdown_to_devto/utils/__init__.py
src/markdown_to_devto/utils/exceptions.py