Metadata-Version: 2.1
Name: markdown-to-devto
Version: 0.3.0.post1
Summary: A CLI tool for publish markdown articles to dev.to
Home-page: https://gitlab.com/hmajid2301/markdown-to-devto
Author: Haseeb Majid
Author-email: hello@haseebmajid.dev
License: Apache License
Keywords: cli,tool
Platform: UNKNOWN
Classifier: Programming Language :: Python
Classifier: Intended Audience :: Developers
Classifier: Operating System :: OS Independent
Classifier: Topic :: Software Development :: Libraries :: Python Modules
Requires-Python: ~=3.6
